MANIFEST.in
README.rst
setup.py
bin/cake
cake/__init__.py
cake/application.py
cake/color.py
cake/errors.py
cake/lib.py
cake.egg-info/PKG-INFO
cake.egg-info/SOURCES.txt
cake.egg-info/dependency_links.txt
cake.egg-info/requires.txt
cake.egg-info/top_level.txt