Metadata-Version: 1.0
Name: cake
Version: 0.2.3
Summary: Minimalistic Python build tool inspired by Rake
Home-page: https://github.com/alexcepoi/cake
Author: Alexandru Cepoi
Author-email: alex.cepoi@gmail.com
License: GPLv3
Download-URL: https://github.com/alexcepoi/cake/zipball/master
Platform: linux
